MANIFEST.in
README.rst
README.txt
aiotarantool.py
setup.py
aiotarantool.egg-info/PKG-INFO
aiotarantool.egg-info/SOURCES.txt
aiotarantool.egg-info/dependency_links.txt
aiotarantool.egg-info/requires.txt
aiotarantool.egg-info/top_level.txt
tests/__init__.py
tests/benchmark.py
tests/benchmark_hot.py
tests/test_aiotarantool.py