Metadata-Version: 1.1
Name: aiotarantool
Version: 1.1.4
Summary: Tarantool connection driver for work with asyncio
Home-page: https://github.com/shveenkov/aiotarantool
Author: Dmitry Shveenkov
Author-email: shveenkov@mail.ru
License: UNKNOWN
Platform: UNKNOWN
Classifier: Programming Language :: Python :: 3.4
Classifier: Intended Audience :: Developers
Classifier: License :: OSI Approved :: GNU Library or Lesser General Public License (LGPL)
Classifier: Operating System :: OS Independent
Classifier: Topic :: Software Development :: Libraries :: Python Modules
Classifier: Topic :: Database :: Front-Ends
